Metadata-Version: 2.1
Name: motherstarter
Version: 2022.4.2
Summary: Network automation inventory data translation tool.
Home-page: https://github.com/writememe/motherstarter
Author: Daniel Teycheney
Author-email: danielfjteycheney@gmail.com
License: Apache License 2.0
Platform: UNKNOWN
Classifier: License :: OSI Approved :: Apache Software License
Classifier: Programming Language :: Python :: 3
Classifier: Programming Language :: Python :: 3.8
Classifier: Programming Language :: Python :: 3.9
Classifier: Operating System :: POSIX :: Linux
Classifier: Operating System :: MacOS
Requires-Python: >=3.8
License-File: LICENSE
License-File: NOTICE
Requires-Dist: bandit (==1.7.4)
Requires-Dist: black (==22.3.0)
Requires-Dist: click (<8.2,>=7.1)
Requires-Dist: colorama (==0.4.4)
Requires-Dist: jinja2 (==3.1.1)
Requires-Dist: mypy (==0.942)
Requires-Dist: nox (==2022.1.7)
Requires-Dist: openpyxl (==3.0.9)
Requires-Dist: pandas (==1.4.1)
Requires-Dist: pylama (==8.3.8)
Requires-Dist: pytest (==7.1.1)
Requires-Dist: pytest-cov (==3.0.0)
Requires-Dist: xlrd (==2.0.1)
Requires-Dist: yamllint (==1.26.3)
Requires-Dist: data-science-types (==0.2.23)
